yob.py
yob_database.py
yob-1.0.0.dist-info/LICENSE
yob-1.0.0.dist-info/METADATA
yob-1.0.0.dist-info/WHEEL
yob-1.0.0.dist-info/top_level.txt
yob-1.0.0.dist-info/RECORD
