Metadata-Version: 2.1
Name: yob
Version: 1.0.0
Summary: Python dictionaries that you can easily save, restore and edit as files
Home-page: https://github.com/pwhipp/yob
Author: Paul Whipp
Author-email: paul.whipp@gmail.com
License: UNKNOWN
Project-URL: Bug Tracker, https://github.com/pwhipp/yob/issues
Platform: UNKNOWN
Classifier: Programming Language :: Python :: 3
Classifier: License :: OSI Approved :: MIT License
Classifier: Operating System :: OS Independent
Requires-Python: >=3.9
License-File: LICENSE
Requires-Dist: PyYAML (==5.4.1)
